cmk/__about__.py
cmk/__init__.py
cmk/_version.py
cmk/common.py
cmk/httpapi.py
cmk/objectapi.py
cmk/objects/__init__.py
cmk/objects/activation_run.py
cmk/objects/attributes.py
cmk/objects/aux_tag.py
cmk/objects/base.py
cmk/objects/bi_aggregation.py
cmk/objects/bi_pack.py
cmk/objects/contact_group_config.py
cmk/objects/dictionary.py
cmk/objects/folder_config.py
cmk/objects/host.py
cmk/objects/host_config.py
cmk/objects/host_group_config.py
cmk/objects/interface/__init__.py
cmk/objects/interface/title.py
cmk/objects/internal.py
cmk/objects/rule.py
cmk/objects/ruleset.py
cmk/objects/service.py
cmk/objects/service_discovery.py
cmk/objects/service_discovery_run.py
cmk/objects/service_group_config.py
cmk/objects/site_connection.py
cmk/objects/user_config.py
cmk/objects/user_role.py
cmk/restapi.py
cmk/util/version.py
python_cmk-24.2.0.dist-info/LICENSE.md
python_cmk-24.2.0.dist-info/METADATA
python_cmk-24.2.0.dist-info/WHEEL
python_cmk-24.2.0.dist-info/RECORD
